sacra/__init__.py
sacra/_print.py
sacra/_version.py
sacra/polyskelion.py
sacra/py.typed
sacra-1.0.0.dist-info/LICENSE
sacra-1.0.0.dist-info/METADATA
sacra-1.0.0.dist-info/WHEEL
sacra-1.0.0.dist-info/entry_points.txt
sacra-1.0.0.dist-info/top_level.txt
sacra-1.0.0.dist-info/RECORD
