Metadata-Version: 2.1
Name: sacra
Version: 1.0.0
Summary: A collection of sacra
Author-email: picafrost <picafrost@proton.me>
License: MIT
Project-URL: Homepage, https://picafrost.com/sacra
Project-URL: Repository, https://github.com/picafrost/sacra
Project-URL: Issues, https://github.com/picafra/sacra/issues
Project-URL: Documentation, https://picafrost.com/sacra
Keywords: sacra
Classifier: License :: OSI Approved :: MIT License
Classifier: Natural Language :: English
Classifier: Programming Language :: Python
Classifier: Programming Language :: Python :: 3.11
Classifier: Programming Language :: Python :: 3.12
Classifier: Programming Language :: Python :: 3.13
Classifier: Topic :: Utilities
Classifier: Topic :: Multimedia
Requires-Python: >=3.11
License-File: LICENSE
Requires-Dist: numpy
Requires-Dist: matplotlib
Provides-Extra: dev
Requires-Dist: mypy; extra == "dev"
Requires-Dist: pytest; extra == "dev"
Requires-Dist: pytest-cov; extra == "dev"
Requires-Dist: ruff; extra == "dev"
